ankirspy-2.1.35.dist-info/METADATA
ankirspy-2.1.35.dist-info/WHEEL
ankirspy.cp37-win_amd64.pyd
ankirspy-2.1.35.dist-info/RECORD
