Metadata-Version: 2.1
Name: ankirspy
Version: 2.1.35
Summary: Anki's Rust library code Python bindings
Author: Ankitects Pty Ltd and contributors <https://help.ankiweb.net>
License: AGPL-3.0-or-later
